breaks/__init__.py
breaks/cli.py
breaks-0.2.0.dist-info/DESCRIPTION.rst
breaks-0.2.0.dist-info/METADATA
breaks-0.2.0.dist-info/RECORD
breaks-0.2.0.dist-info/WHEEL
breaks-0.2.0.dist-info/entry_points.txt
breaks-0.2.0.dist-info/metadata.json
breaks-0.2.0.dist-info/top_level.txt
breaks-0.2.0.dist-info/zip-safe
