Metadata-Version: 2.0
Name: breaks
Version: 0.2.0
Summary: calculate bins on spatial data
Home-page: https://github.com/fitnr/breaks
Author: fitnr
Author-email: contact@fakeisthenewreal.org
License: GPL
Keywords: gis geodata chloropleth
Platform: UNKNOWN
Classifier: Development Status :: 4 - Beta
Classifier: License :: OSI Approved :: GNU General Public License v3 (GPLv3)
Classifier: Natural Language :: English
Classifier: Programming Language :: Python :: 2.7
Classifier: Programming Language :: Python :: 3.3
Classifier: Programming Language :: Python :: 3.4
Classifier: Operating System :: OS Independent
Requires-Dist: click (>=6.2,<7)
Requires-Dist: fiona (>=1.6.0,<2.0)
Requires-Dist: fionautil (>=0.5.1,<0.6.0)
Requires-Dist: numpy (>=1.10.4,<1.11)
Requires-Dist: pysal (>=1.11.0,<1.12)
Requires-Dist: scipy (>=0.15.1,<0.20)
